Metadata-Version: 2.1
Name: fcn-f0-data-fcn-929
Version: 1.0.0
Summary: FCN-929 coefficient HDF5 data file
License: MIT License
Classifier: License :: OSI Approved :: MIT License
License-File: LICENSE
